CHANGELOG.md
LICENSE
MANIFEST.in
README.md
requirements.txt
setup.cfg
setup.py
playmate/__init__.py
playmate/api.py
playmate/constants.py
playmate/lists.py
playmate/scraper.py
playmate/settings.py
playmate/utils.py
playmate.egg-info/PKG-INFO
playmate.egg-info/SOURCES.txt
playmate.egg-info/dependency_links.txt
playmate.egg-info/requires.txt
playmate.egg-info/top_level.txt