Metadata-Version: 2.1
Name: playmate
Version: 0.5.6
Summary: Google Play Store async application scraper
Home-page: https://github.com/Gulats/playmate
Author: Bharat Gulati
Author-email: bharat.gulati.certi@gmail.com
License: MIT License
Platform: UNKNOWN
Classifier: Development Status :: 3 - Alpha
Classifier: Intended Audience :: Developers
Classifier: License :: OSI Approved :: MIT License
Classifier: Natural Language :: English
Classifier: Operating System :: OS Independent
Classifier: Programming Language :: Python :: 3.7
